horizonai/__init__.py
horizonai/base.py
horizonai/cli.py
horizonai/enabler.py
horizonai/project.py
horizonai/task.py
horizonai/user.py
horizonai-0.1.19.dist-info/LICENSE
horizonai-0.1.19.dist-info/METADATA
horizonai-0.1.19.dist-info/WHEEL
horizonai-0.1.19.dist-info/entry_points.txt
horizonai-0.1.19.dist-info/top_level.txt
horizonai-0.1.19.dist-info/RECORD
